pierogis_rs.cpython-38-darwin.so
pyrogis/__init__.py
pyrogis/__main__.py
pyrogis/course.py
pyrogis/restaurant.py
pyrogis/ingredients/__init__.py
pyrogis/ingredients/crop.py
pyrogis/ingredients/dish.py
pyrogis/ingredients/flip.py
pyrogis/ingredients/ingredient.py
pyrogis/ingredients/pierogi.py
pyrogis/ingredients/quantize.py
pyrogis/ingredients/recipe.py
pyrogis/ingredients/resize.py
pyrogis/ingredients/rotate.py
pyrogis/ingredients/sort.py
pyrogis/ingredients/seasonings/__init__.py
pyrogis/ingredients/seasonings/cartography.py
pyrogis/ingredients/seasonings/rectangle.py
pyrogis/ingredients/seasonings/seasoning.py
pyrogis/ingredients/seasonings/threshold.py
pyrogis/kitchen/__init__.py
pyrogis/kitchen/chef.py
pyrogis/kitchen/kitchen.py
pyrogis/kitchen/order.py
pyrogis/kitchen/server.py
pyrogis/kitchen/ticket.py
pyrogis/kitchen/menu/__init__.py
pyrogis/kitchen/menu/crop_filling.py
pyrogis/kitchen/menu/custom_filling.py
pyrogis/kitchen/menu/filling.py
pyrogis/kitchen/menu/quantize_filling.py
pyrogis/kitchen/menu/resize_filling.py
pyrogis/kitchen/menu/rotate_filling.py
pyrogis/kitchen/menu/sort_filling.py
pyrogis/kitchen/menu/threshold_filling.py
pyrogis-0.3.2.dist-info/LICENSE
pyrogis-0.3.2.dist-info/METADATA
pyrogis-0.3.2.dist-info/WHEEL
pyrogis-0.3.2.dist-info/entry_points.txt
pyrogis-0.3.2.dist-info/top_level.txt
pyrogis-0.3.2.dist-info/RECORD
